{"problem":451,"k":27,"n":36887,"chain":[{"start":55,"end":80,"p":53,"q":1},{"start":81,"end":101,"p":37,"q":2},{"start":102,"end":121,"p":47,"q":2},{"start":122,"end":143,"p":29,"q":4},{"start":144,"end":168,"p":47,"q":3},{"start":169,"end":191,"p":41,"q":4},{"start":192,"end":215,"p":47,"q":4},{"start":216,"end":242,"p":43,"q":5},{"start":243,"end":262,"p":47,"q":5},{"start":263,"end":288,"p":29,"q":9},{"start":289,"end":314,"p":41,"q":7},{"start":315,"end":337,"p":31,"q":10},{"start":338,"end":360,"p":37,"q":9},{"start":361,"end":375,"p":29,"q":12},{"start":376,"end":399,"p":31,"q":12},{"start":400,"end":414,"p":43,"q":9},{"start":415,"end":437,"p":41,"q":10},{"start":438,"end":462,"p":29,"q":15},{"start":463,"end":478,"p":41,"q":11},{"start":479,"end":504,"p":53,"q":9},{"start":505,"end":523,"p":31,"q":16},{"start":524,"end":549,"p":29,"q":18},{"start":550,"end":560,"p":41,"q":13},{"start":561,"end":586,"p":43,"q":13},{"start":587,"end":610,"p":53,"q":11},{"start":611,"end":636,"p":29,"q":21},{"start":637,"end":663,"p":53,"q":12},{"start":664,"end":685,"p":47,"q":14},{"start":686,"end":709,"p":31,"q":22},{"start":710,"end":732,"p":47,"q":15},{"start":733,"end":758,"p":43,"q":17},{"start":759,"end":781,"p":29,"q":26},{"start":782,"end":806,"p":41,"q":19},{"start":807,"end":833,"p":31,"q":26},{"start":834,"end":847,"p":41,"q":20},{"start":848,"end":873,"p":47,"q":18},{"start":874,"end":897,"p":29,"q":30},{"start":898,"end":920,"p":47,"q":19},{"start":921,"end":930,"p":43,"q":21},{"start":931,"end":957,"p":31,"q":30},{"start":958,"end":984,"p":29,"q":33},{"start":985,"end":1011,"p":41,"q":24},{"start":1012,"end":1034,"p":53,"q":19},{"start":1035,"end":1061,"p":47,"q":22},{"start":1062,"end":1087,"p":53,"q":20},{"start":1088,"end":1112,"p":31,"q":35},{"start":1113,"end":1137,"p":37,"q":30},{"start":1138,"end":1158,"p":29,"q":39},{"start":1159,"end":1175,"p":41,"q":28},{"start":1176,"end":1202,"p":47,"q":25},{"start":1203,"end":1216,"p":29,"q":41},{"start":1217,"end":1236,"p":31,"q":39},{"start":1237,"end":1257,"p":41,"q":30},{"start":1258,"end":1274,"p":29,"q":43},{"start":1275,"end":1299,"p":53,"q":24},{"start":1300,"end":1322,"p":37,"q":35},{"start":1323,"end":1343,"p":47,"q":28},{"start":1344,"end":1361,"p":29,"q":46},{"start":1362,"end":1380,"p":41,"q":33},{"start":1381,"end":1405,"p":53,"q":26},{"start":1406,"end":1422,"p":31,"q":45},{"start":1423,"end":1448,"p":29,"q":49},{"start":1449,"end":1470,"p":37,"q":39},{"start":1471,"end":1489,"p":43,"q":34},{"start":1490,"end":1515,"p":31,"q":48},{"start":1516,"end":1535,"p":29,"q":52},{"start":1536,"end":1546,"p":31,"q":49},{"start":1547,"end":1564,"p":29,"q":53},{"start":1565,"end":1585,"p":41,"q":38},{"start":1586,"end":1608,"p":31,"q":51},{"start":1609,"end":1626,"p":41,"q":39},{"start":1627,"end":1651,"p":29,"q":56},{"start":1652,"end":1672,"p":47,"q":35},{"start":1673,"end":1692,"p":37,"q":45},{"start":1693,"end":1719,"p":47,"q":36},{"start":1720,"end":1738,"p":29,"q":59},{"start":1739,"end":1763,"p":31,"q":56},{"start":1764,"end":1790,"p":41,"q":43},{"start":1791,"end":1813,"p":47,"q":38},{"start":1814,"end":1840,"p":37,"q":49},{"start":1841,"end":1860,"p":47,"q":39},{"start":1861,"end":1887,"p":31,"q":60},{"start":1888,"end":1914,"p":37,"q":51},{"start":1915,"end":1941,"p":29,"q":66},{"start":1942,"end":1962,"p":43,"q":45},{"start":1963,"end":1988,"p":37,"q":53},{"start":1989,"end":2011,"p":31,"q":64},{"start":2012,"end":2036,"p":41,"q":49},{"start":2037,"end":2062,"p":37,"q":55},{"start":2063,"end":2086,"p":29,"q":71},{"start":2087,"end":2104,"p":31,"q":67},{"start":2105,"end":2118,"p":41,"q":51},{"start":2119,"end":2144,"p":29,"q":73},{"start":2145,"end":2166,"p":31,"q":69},{"start":2167,"end":2189,"p":47,"q":46},{"start":2190,"end":2210,"p":37,"q":59},{"start":2211,"end":2236,"p":47,"q":47},{"start":2237,"end":2263,"p":43,"q":52},{"start":2264,"end":2290,"p":31,"q":73},{"start":2291,"end":2306,"p":43,"q":53},{"start":2307,"end":2330,"p":47,"q":49},{"start":2331,"end":2352,"p":31,"q":75},{"start":2353,"end":2377,"p":47,"q":50},{"start":2378,"end":2395,"p":37,"q":64},{"start":2396,"end":2414,"p":31,"q":77},{"start":2415,"end":2435,"p":43,"q":56},{"start":2436,"end":2446,"p":41,"q":59},{"start":2447,"end":2471,"p":47,"q":52},{"start":2472,"end":2492,"p":29,"q":85},{"start":2493,"end":2518,"p":47,"q":53},{"start":2519,"end":2543,"p":37,"q":68},{"start":2544,"end":2569,"p":31,"q":82},{"start":2570,"end":2580,"p":37,"q":69},{"start":2581,"end":2607,"p":43,"q":60},{"start":2608,"end":2631,"p":31,"q":84},{"start":2632,"end":2654,"p":37,"q":71},{"start":2655,"end":2677,"p":53,"q":50},{"start":2678,"end":2695,"p":29,"q":92},{"start":2696,"end":2706,"p":47,"q":57},{"start":2707,"end":2733,"p":41,"q":66},{"start":2734,"end":2755,"p":31,"q":88},{"start":2756,"end":2782,"p":29,"q":95},{"start":2783,"end":2802,"p":37,"q":75},{"start":2803,"end":2822,"p":43,"q":65},{"start":2823,"end":2848,"p":31,"q":91},{"start":2849,"end":2869,"p":29,"q":98},{"start":2870,"end":2894,"p":47,"q":61},{"start":2895,"end":2913,"p":37,"q":78},{"start":2914,"end":2938,"p":41,"q":71},{"start":2939,"end":2956,"p":29,"q":101},{"start":2957,"end":2979,"p":41,"q":72},{"start":2980,"end":3003,"p":31,"q":96},{"start":3004,"end":3024,"p":37,"q":81},{"start":3025,"end":3048,"p":53,"q":57},{"start":3049,"end":3072,"p":29,"q":105},{"start":3073,"end":3098,"p":37,"q":83},{"start":3099,"end":3123,"p":43,"q":72},{"start":3124,"end":3143,"p":41,"q":76},{"start":3144,"end":3166,"p":43,"q":73},{"start":3167,"end":3189,"p":31,"q":102},{"start":3190,"end":3209,"p":37,"q":86},{"start":3210,"end":3225,"p":41,"q":78},{"start":3226,"end":3252,"p":43,"q":75},{"start":3253,"end":3275,"p":29,"q":112},{"start":3276,"end":3295,"p":43,"q":76},{"start":3296,"end":3320,"p":37,"q":89},{"start":3321,"end":3344,"p":31,"q":107},{"start":3345,"end":3366,"p":53,"q":63},{"start":3367,"end":3391,"p":29,"q":116},{"start":3392,"end":3411,"p":47,"q":72},{"start":3412,"end":3437,"p":31,"q":110},{"start":3438,"end":3458,"p":47,"q":73},{"start":3459,"end":3478,"p":29,"q":119},{"start":3479,"end":3505,"p":37,"q":94},{"start":3506,"end":3530,"p":31,"q":113},{"start":3531,"end":3553,"p":41,"q":86},{"start":3554,"end":3579,"p":37,"q":96},{"start":3580,"end":3599,"p":47,"q":76},{"start":3600,"end":3623,"p":29,"q":124},{"start":3624,"end":3646,"p":47,"q":77},{"start":3647,"end":3654,"p":31,"q":117},{"start":3655,"end":3681,"p":29,"q":126},{"start":3682,"end":3693,"p":47,"q":78},{"start":3694,"end":3717,"p":41,"q":90},{"start":3718,"end":3740,"p":47,"q":79},{"start":3741,"end":3764,"p":37,"q":101},{"start":3765,"end":3790,"p":53,"q":71},{"start":3791,"end":3811,"p":43,"q":88},{"start":3812,"end":3838,"p":37,"q":103},{"start":3839,"end":3855,"p":29,"q":132},{"start":3856,"end":3881,"p":41,"q":94},{"start":3882,"end":3902,"p":31,"q":125},{"start":3903,"end":3928,"p":47,"q":83},{"start":3929,"end":3949,"p":37,"q":106},{"start":3950,"end":3975,"p":47,"q":84},{"start":3976,"end":4002,"p":53,"q":75},{"start":4003,"end":4029,"p":29,"q":138},{"start":4030,"end":4055,"p":53,"q":76},{"start":4056,"end":4069,"p":43,"q":94},{"start":4070,"end":4088,"p":31,"q":131},{"start":4089,"end":4112,"p":43,"q":95},{"start":4113,"end":4134,"p":37,"q":111},{"start":4135,"end":4161,"p":53,"q":78},{"start":4162,"end":4181,"p":31,"q":134},{"start":4182,"end":4208,"p":37,"q":113},{"start":4209,"end":4232,"p":29,"q":145},{"start":4233,"end":4257,"p":47,"q":90},{"start":4258,"end":4284,"p":43,"q":99},{"start":4285,"end":4305,"p":31,"q":138},{"start":4306,"end":4332,"p":41,"q":105},{"start":4333,"end":4356,"p":37,"q":117},{"start":4357,"end":4377,"p":29,"q":150},{"start":4378,"end":4398,"p":31,"q":141},{"start":4399,"end":4414,"p":41,"q":107},{"start":4415,"end":4435,"p":29,"q":152},{"start":4436,"end":4460,"p":31,"q":143},{"start":4461,"end":4479,"p":53,"q":84},{"start":4480,"end":4504,"p":37,"q":121},{"start":4505,"end":4522,"p":29,"q":155},{"start":4523,"end":4542,"p":43,"q":105},{"start":4543,"end":4553,"p":31,"q":146},{"start":4554,"end":4580,"p":29,"q":157},{"start":4581,"end":4586,"p":47,"q":97},{"start":4587,"end":4609,"p":29,"q":158},{"start":4610,"end":4633,"p":47,"q":98},{"start":4634,"end":4660,"p":41,"q":113},{"start":4661,"end":4680,"p":47,"q":99},{"start":4681,"end":4701,"p":41,"q":114},{"start":4702,"end":4727,"p":47,"q":100},{"start":4728,"end":4754,"p":29,"q":163},{"start":4755,"end":4774,"p":47,"q":101},{"start":4775,"end":4801,"p":31,"q":154},{"start":4802,"end":4824,"p":41,"q":117},{"start":4825,"end":4850,"p":53,"q":91},{"start":4851,"end":4874,"p":37,"q":131},{"start":4875,"end":4899,"p":29,"q":168},{"start":4900,"end":4925,"p":31,"q":158},{"start":4926,"end":4948,"p":37,"q":133},{"start":4949,"end":4972,"p":43,"q":115},{"start":4973,"end":4988,"p":41,"q":121},{"start":4989,"end":5015,"p":29,"q":172},{"start":5016,"end":5029,"p":41,"q":122},{"start":5030,"end":5056,"p":47,"q":107},{"start":5057,"end":5080,"p":31,"q":163},{"start":5081,"end":5103,"p":47,"q":108},{"start":5104,"end":5115,"p":53,"q":96},{"start":5116,"end":5142,"p":31,"q":165},{"start":5143,"end":5168,"p":53,"q":97},{"start":5169,"end":5193,"p":41,"q":126},{"start":5194,"end":5218,"p":29,"q":179},{"start":5219,"end":5244,"p":37,"q":141},{"start":5245,"end":5266,"p":31,"q":169},{"start":5267,"end":5291,"p":47,"q":112},{"start":5292,"end":5318,"p":37,"q":143},{"start":5319,"end":5338,"p":47,"q":113},{"start":5339,"end":5363,"p":29,"q":184},{"start":5364,"end":5390,"p":31,"q":173},{"start":5391,"end":5402,"p":43,"q":125},{"start":5403,"end":5429,"p":37,"q":146},{"start":5430,"end":5452,"p":31,"q":175},{"start":5453,"end":5479,"p":29,"q":188},{"start":5480,"end":5503,"p":37,"q":148},{"start":5504,"end":5526,"p":47,"q":117},{"start":5527,"end":5545,"p":31,"q":178},{"start":5546,"end":5566,"p":29,"q":191},{"start":5567,"end":5592,"p":53,"q":105},{"start":5593,"end":5617,"p":43,"q":130},{"start":5618,"end":5644,"p":41,"q":137},{"start":5645,"end":5669,"p":31,"q":182},{"start":5670,"end":5688,"p":37,"q":153},{"start":5689,"end":5714,"p":47,"q":121},{"start":5715,"end":5740,"p":29,"q":197},{"start":5741,"end":5767,"p":41,"q":140},{"start":5768,"end":5793,"p":31,"q":186},{"start":5794,"end":5808,"p":41,"q":141},{"start":5809,"end":5832,"p":43,"q":135},{"start":5833,"end":5857,"p":53,"q":110},{"start":5858,"end":5875,"p":43,"q":136},{"start":5876,"end":5902,"p":47,"q":125},{"start":5903,"end":5918,"p":43,"q":137},{"start":5919,"end":5943,"p":29,"q":204},{"start":5944,"end":5963,"p":53,"q":112},{"start":5964,"end":5984,"p":37,"q":161},{"start":5985,"end":6010,"p":31,"q":193},{"start":6011,"end":6030,"p":29,"q":207},{"start":6031,"end":6054,"p":41,"q":147},{"start":6055,"end":6072,"p":31,"q":195},{"start":6073,"end":6095,"p":37,"q":164},{"start":6096,"end":6122,"p":53,"q":115},{"start":6123,"end":6146,"p":29,"q":211},{"start":6147,"end":6169,"p":37,"q":166},{"start":6170,"end":6196,"p":31,"q":199},{"start":6197,"end":6219,"p":43,"q":144},{"start":6220,"end":6243,"p":37,"q":168},{"start":6244,"end":6262,"p":29,"q":215},{"start":6263,"end":6289,"p":31,"q":202},{"start":6290,"end":6305,"p":43,"q":146},{"start":6306,"end":6325,"p":47,"q":134},{"start":6326,"end":6351,"p":31,"q":204},{"start":6352,"end":6378,"p":29,"q":219},{"start":6379,"end":6391,"p":37,"q":172},{"start":6392,"end":6413,"p":31,"q":206},{"start":6414,"end":6440,"p":53,"q":121},{"start":6441,"end":6466,"p":47,"q":137},{"start":6467,"end":6493,"p":53,"q":122},{"start":6494,"end":6520,"p":43,"q":151},{"start":6521,"end":6546,"p":41,"q":159},{"start":6547,"end":6568,"p":31,"q":211},{"start":6569,"end":6587,"p":41,"q":160},{"start":6588,"end":6613,"p":37,"q":178},{"start":6614,"end":6639,"p":29,"q":228},{"start":6640,"end":6661,"p":31,"q":214},{"start":6662,"end":6687,"p":37,"q":180},{"start":6688,"end":6710,"p":41,"q":163},{"start":6711,"end":6735,"p":43,"q":156},{"start":6736,"end":6761,"p":37,"q":182},{"start":6762,"end":6785,"p":31,"q":218},{"start":6786,"end":6811,"p":53,"q":128},{"start":6812,"end":6835,"p":37,"q":184},{"start":6836,"end":6847,"p":31,"q":220},{"start":6848,"end":6874,"p":41,"q":167},{"start":6875,"end":6900,"p":29,"q":237},{"start":6901,"end":6917,"p":53,"q":130},{"start":6918,"end":6940,"p":31,"q":223},{"start":6941,"end":6958,"p":29,"q":239},{"start":6959,"end":6983,"p":37,"q":188},{"start":6984,"end":7002,"p":31,"q":225},{"start":7003,"end":7023,"p":53,"q":132},{"start":7024,"end":7045,"p":29,"q":242},{"start":7046,"end":7064,"p":31,"q":227},{"start":7065,"end":7079,"p":41,"q":172},{"start":7080,"end":7103,"p":29,"q":244},{"start":7104,"end":7129,"p":53,"q":134},{"start":7130,"end":7132,"p":29,"q":245},{"start":7133,"end":7157,"p":31,"q":230},{"start":7158,"end":7182,"p":53,"q":135},{"start":7183,"end":7208,"p":43,"q":167},{"start":7209,"end":7235,"p":53,"q":136},{"start":7236,"end":7251,"p":43,"q":168},{"start":7252,"end":7277,"p":29,"q":250},{"start":7278,"end":7294,"p":43,"q":169},{"start":7295,"end":7316,"p":37,"q":197},{"start":7317,"end":7343,"p":31,"q":236},{"start":7344,"end":7366,"p":41,"q":179},{"start":7367,"end":7393,"p":29,"q":254},{"start":7394,"end":7407,"p":41,"q":180},{"start":7408,"end":7427,"p":37,"q":200},{"start":7428,"end":7453,"p":47,"q":158},{"start":7454,"end":7480,"p":29,"q":257},{"start":7481,"end":7501,"p":37,"q":202},{"start":7502,"end":7509,"p":29,"q":258},{"start":7510,"end":7530,"p":41,"q":183},{"start":7531,"end":7553,"p":53,"q":142},{"start":7554,"end":7575,"p":37,"q":204},{"start":7576,"end":7596,"p":29,"q":261},{"start":7597,"end":7622,"p":31,"q":245},{"start":7623,"end":7649,"p":37,"q":206},{"start":7650,"end":7659,"p":53,"q":144},{"start":7660,"end":7686,"p":37,"q":207},{"start":7687,"end":7712,"p":29,"q":265},{"start":7713,"end":7735,"p":41,"q":188},{"start":7736,"end":7760,"p":37,"q":209},{"start":7761,"end":7782,"p":47,"q":165},{"start":7783,"end":7808,"p":31,"q":251},{"start":7809,"end":7834,"p":37,"q":211},{"start":7835,"end":7858,"p":41,"q":191},{"start":7859,"end":7876,"p":47,"q":167},{"start":7877,"end":7901,"p":31,"q":254},{"start":7902,"end":7924,"p":53,"q":149},{"start":7925,"end":7945,"p":37,"q":214},{"start":7946,"end":7970,"p":47,"q":169},{"start":7971,"end":7994,"p":31,"q":257},{"start":7995,"end":8019,"p":37,"q":216},{"start":8020,"end":8031,"p":29,"q":276},{"start":8032,"end":8056,"p":31,"q":259},{"start":8057,"end":8083,"p":53,"q":152},{"start":8084,"end":8104,"p":41,"q":197},{"start":8105,"end":8130,"p":37,"q":219},{"start":8131,"end":8154,"p":43,"q":189},{"start":8155,"end":8180,"p":31,"q":263},{"start":8181,"end":8205,"p":29,"q":282},{"start":8206,"end":8227,"p":41,"q":200},{"start":8228,"end":8252,"p":47,"q":175},{"start":8253,"end":8278,"p":37,"q":223},{"start":8279,"end":8304,"p":31,"q":267},{"start":8305,"end":8326,"p":43,"q":193},{"start":8327,"end":8352,"p":37,"q":225},{"start":8353,"end":8379,"p":29,"q":288},{"start":8380,"end":8401,"p":53,"q":158},{"start":8402,"end":8428,"p":31,"q":271},{"start":8429,"end":8455,"p":43,"q":196},{"start":8456,"end":8473,"p":41,"q":206},{"start":8474,"end":8500,"p":37,"q":229},{"start":8501,"end":8524,"p":29,"q":293},{"start":8525,"end":8541,"p":43,"q":198},{"start":8542,"end":8560,"p":53,"q":161},{"start":8561,"end":8584,"p":43,"q":199},{"start":8585,"end":8611,"p":29,"q":296},{"start":8612,"end":8637,"p":41,"q":210},{"start":8638,"end":8648,"p":37,"q":233},{"start":8649,"end":8675,"p":47,"q":184},{"start":8676,"end":8698,"p":29,"q":299},{"start":8699,"end":8722,"p":37,"q":235},{"start":8723,"end":8738,"p":31,"q":281},{"start":8739,"end":8760,"p":41,"q":213},{"start":8761,"end":8785,"p":29,"q":302},{"start":8786,"end":8801,"p":41,"q":214},{"start":8802,"end":8825,"p":53,"q":166},{"start":8826,"end":8843,"p":29,"q":304},{"start":8844,"end":8870,"p":37,"q":239},{"start":8871,"end":8893,"p":31,"q":286},{"start":8894,"end":8910,"p":47,"q":189},{"start":8911,"end":8931,"p":53,"q":168},{"start":8932,"end":8957,"p":47,"q":190},{"start":8958,"end":8984,"p":53,"q":169},{"start":8985,"end":9006,"p":41,"q":219},{"start":9007,"end":9018,"p":37,"q":243},{"start":9019,"end":9037,"p":53,"q":170},{"start":9038,"end":9057,"p":43,"q":210},{"start":9058,"end":9079,"p":31,"q":292},{"start":9080,"end":9104,"p":29,"q":313},{"start":9105,"end":9129,"p":37,"q":246},{"start":9130,"end":9145,"p":47,"q":194},{"start":9146,"end":9172,"p":31,"q":295},{"start":9173,"end":9196,"p":53,"q":173},{"start":9197,"end":9220,"p":29,"q":317},{"start":9221,"end":9240,"p":37,"q":249},{"start":9241,"end":9265,"p":31,"q":298},{"start":9266,"end":9286,"p":47,"q":197},{"start":9287,"end":9307,"p":29,"q":320},{"start":9308,"end":9334,"p":41,"q":227},{"start":9335,"end":9358,"p":31,"q":301},{"start":9359,"end":9380,"p":47,"q":199},{"start":9381,"end":9401,"p":43,"q":218},{"start":9402,"end":9427,"p":47,"q":200},{"start":9428,"end":9452,"p":29,"q":325},{"start":9453,"end":9474,"p":47,"q":201},{"start":9475,"end":9499,"p":37,"q":256},{"start":9500,"end":9521,"p":47,"q":202},{"start":9522,"end":9544,"p":31,"q":307},{"start":9545,"end":9568,"p":29,"q":329},{"start":9569,"end":9580,"p":41,"q":233},{"start":9581,"end":9606,"p":31,"q":309},{"start":9607,"end":9626,"p":29,"q":331},{"start":9627,"end":9647,"p":37,"q":260},{"start":9648,"end":9673,"p":53,"q":182},{"start":9674,"end":9699,"p":31,"q":312},{"start":9700,"end":9726,"p":53,"q":183},{"start":9727,"end":9745,"p":43,"q":226},{"start":9746,"end":9771,"p":29,"q":336},{"start":9772,"end":9795,"p":37,"q":264},{"start":9796,"end":9803,"p":47,"q":208},{"start":9804,"end":9829,"p":29,"q":338},{"start":9830,"end":9854,"p":31,"q":317},{"start":9855,"end":9874,"p":43,"q":229},{"start":9875,"end":9897,"p":47,"q":210},{"start":9898,"end":9917,"p":43,"q":230},{"start":9918,"end":9944,"p":47,"q":211},{"start":9945,"end":9960,"p":43,"q":231},{"start":9961,"end":9980,"p":37,"q":269},{"start":9981,"end":10003,"p":29,"q":344},{"start":10004,"end":10017,"p":37,"q":270},{"start":10018,"end":10044,"p":53,"q":189},{"start":10045,"end":10071,"p":31,"q":324},{"start":10072,"end":10097,"p":53,"q":190},{"start":10098,"end":10119,"p":29,"q":348},{"start":10120,"end":10133,"p":31,"q":326},{"start":10134,"end":10154,"p":41,"q":247},{"start":10155,"end":10179,"p":47,"q":216},{"start":10180,"end":10206,"p":29,"q":351},{"start":10207,"end":10226,"p":31,"q":329},{"start":10227,"end":10239,"p":37,"q":276},{"start":10240,"end":10264,"p":29,"q":353},{"start":10265,"end":10288,"p":31,"q":331},{"start":10289,"end":10313,"p":37,"q":278},{"start":10314,"end":10322,"p":29,"q":355},{"start":10323,"end":10347,"p":43,"q":240},{"start":10348,"end":10367,"p":47,"q":220},{"start":10368,"end":10390,"p":43,"q":241},{"start":10391,"end":10415,"p":53,"q":196},{"start":10416,"end":10441,"p":41,"q":254},{"start":10442,"end":10468,"p":53,"q":197},{"start":10469,"end":10482,"p":41,"q":255},{"start":10483,"end":10508,"p":47,"q":223},{"start":10509,"end":10535,"p":37,"q":284},{"start":10536,"end":10562,"p":43,"q":245},{"start":10563,"end":10583,"p":29,"q":364},{"start":10584,"end":10609,"p":37,"q":286},{"start":10610,"end":10629,"p":31,"q":342},{"start":10630,"end":10649,"p":47,"q":226},{"start":10650,"end":10670,"p":29,"q":367},{"start":10671,"end":10696,"p":47,"q":227},{"start":10697,"end":10722,"p":31,"q":345},{"start":10723,"end":10743,"p":47,"q":228},{"start":10744,"end":10769,"p":41,"q":262},{"start":10770,"end":10794,"p":37,"q":291},{"start":10795,"end":10820,"p":43,"q":251},{"start":10821,"end":10846,"p":31,"q":349},{"start":10847,"end":10873,"p":29,"q":374},{"start":10874,"end":10892,"p":41,"q":265},{"start":10893,"end":10908,"p":31,"q":351},{"start":10909,"end":10933,"p":41,"q":266},{"start":10934,"end":10960,"p":29,"q":377},{"start":10961,"end":10979,"p":37,"q":296},{"start":10980,"end":11001,"p":31,"q":354},{"start":11002,"end":11025,"p":47,"q":234},{"start":11026,"end":11051,"p":53,"q":208},{"start":11052,"end":11078,"p":43,"q":257},{"start":11079,"end":11105,"p":29,"q":382},{"start":11106,"end":11127,"p":37,"q":300},{"start":11128,"end":11138,"p":41,"q":271},{"start":11139,"end":11164,"p":37,"q":301},{"start":11165,"end":11187,"p":31,"q":360},{"start":11188,"end":11213,"p":47,"q":238},{"start":11214,"end":11238,"p":37,"q":303},{"start":11239,"end":11263,"p":53,"q":212},{"start":11264,"end":11280,"p":31,"q":363},{"start":11281,"end":11307,"p":47,"q":240},{"start":11308,"end":11316,"p":53,"q":213},{"start":11317,"end":11343,"p":41,"q":276},{"start":11344,"end":11369,"p":53,"q":214},{"start":11370,"end":11395,"p":29,"q":392},{"start":11396,"end":11422,"p":43,"q":265},{"start":11423,"end":11448,"p":47,"q":243},{"start":11449,"end":11475,"p":53,"q":216},{"start":11476,"end":11497,"p":31,"q":370},{"start":11498,"end":11511,"p":29,"q":396},{"start":11512,"end":11534,"p":37,"q":311},{"start":11535,"end":11559,"p":31,"q":372},{"start":11560,"end":11581,"p":53,"q":218},{"start":11582,"end":11608,"p":37,"q":313},{"start":11609,"end":11634,"p":53,"q":219},{"start":11635,"end":11656,"p":29,"q":401},{"start":11657,"end":11683,"p":31,"q":376},{"start":11684,"end":11687,"p":53,"q":220},{"start":11688,"end":11714,"p":29,"q":403},{"start":11715,"end":11740,"p":53,"q":221},{"start":11741,"end":11766,"p":43,"q":273},{"start":11767,"end":11793,"p":37,"q":318},{"start":11794,"end":11809,"p":43,"q":274},{"start":11810,"end":11835,"p":41,"q":288},{"start":11836,"end":11859,"p":29,"q":408},{"start":11860,"end":11876,"p":41,"q":289},{"start":11877,"end":11900,"p":31,"q":383},{"start":11901,"end":11918,"p":47,"q":253},{"start":11919,"end":11941,"p":37,"q":322},{"start":11942,"end":11965,"p":47,"q":254},{"start":11966,"end":11981,"p":43,"q":278},{"start":11982,"end":12005,"p":53,"q":226},{"start":12006,"end":12024,"p":31,"q":387},{"start":12025,"end":12040,"p":41,"q":293},{"start":12041,"end":12067,"p":43,"q":280},{"start":12068,"end":12091,"p":29,"q":416},{"start":12092,"end":12117,"p":31,"q":390},{"start":12118,"end":12126,"p":37,"q":327},{"start":12127,"end":12153,"p":43,"q":282},{"start":12154,"end":12179,"p":31,"q":392},{"start":12180,"end":12204,"p":41,"q":297},{"start":12205,"end":12217,"p":53,"q":230},{"start":12218,"end":12241,"p":31,"q":394},{"start":12242,"end":12265,"p":29,"q":422},{"start":12266,"end":12286,"p":41,"q":299},{"start":12287,"end":12311,"p":37,"q":332},{"start":12312,"end":12334,"p":31,"q":397},{"start":12335,"end":12352,"p":29,"q":425},{"start":12353,"end":12376,"p":53,"q":233},{"start":12377,"end":12396,"p":31,"q":399},{"start":12397,"end":12422,"p":37,"q":335},{"start":12423,"end":12439,"p":29,"q":428},{"start":12440,"end":12459,"p":37,"q":336},{"start":12460,"end":12482,"p":47,"q":265},{"start":12483,"end":12497,"p":29,"q":430},{"start":12498,"end":12520,"p":31,"q":403},{"start":12521,"end":12540,"p":43,"q":291},{"start":12541,"end":12555,"p":29,"q":432},{"start":12556,"end":12582,"p":31,"q":405},{"start":12583,"end":12607,"p":37,"q":340},{"start":12608,"end":12626,"p":43,"q":293},{"start":12627,"end":12644,"p":31,"q":407},{"start":12645,"end":12671,"p":29,"q":436},{"start":12672,"end":12696,"p":41,"q":309},{"start":12697,"end":12718,"p":37,"q":343},{"start":12719,"end":12737,"p":31,"q":410},{"start":12738,"end":12764,"p":47,"q":271},{"start":12765,"end":12787,"p":29,"q":440},{"start":12788,"end":12811,"p":47,"q":272},{"start":12812,"end":12830,"p":31,"q":413},{"start":12831,"end":12853,"p":53,"q":242},{"start":12854,"end":12874,"p":29,"q":443},{"start":12875,"end":12901,"p":41,"q":314},{"start":12902,"end":12927,"p":43,"q":300},{"start":12928,"end":12954,"p":31,"q":417},{"start":12955,"end":12977,"p":37,"q":350},{"start":12978,"end":12999,"p":47,"q":276},{"start":13000,"end":13024,"p":41,"q":317},{"start":13025,"end":13051,"p":37,"q":352},{"start":13052,"end":13078,"p":31,"q":421},{"start":13079,"end":13099,"p":43,"q":304},{"start":13100,"end":13125,"p":37,"q":354},{"start":13126,"end":13147,"p":41,"q":320},{"start":13148,"end":13171,"p":31,"q":424},{"start":13172,"end":13193,"p":29,"q":454},{"start":13194,"end":13202,"p":31,"q":425},{"start":13203,"end":13229,"p":41,"q":322},{"start":13230,"end":13251,"p":29,"q":456},{"start":13252,"end":13277,"p":53,"q":250},{"start":13278,"end":13295,"p":31,"q":428},{"start":13296,"end":13314,"p":43,"q":309},{"start":13315,"end":13338,"p":29,"q":459},{"start":13339,"end":13357,"p":31,"q":430},{"start":13358,"end":13384,"p":37,"q":361},{"start":13385,"end":13400,"p":43,"q":311},{"start":13401,"end":13425,"p":29,"q":462},{"start":13426,"end":13450,"p":31,"q":433},{"start":13451,"end":13475,"p":41,"q":328},{"start":13476,"end":13495,"p":37,"q":364},{"start":13496,"end":13516,"p":41,"q":329},{"start":13517,"end":13543,"p":31,"q":436},{"start":13544,"end":13570,"p":29,"q":467},{"start":13571,"end":13595,"p":53,"q":256},{"start":13596,"end":13615,"p":43,"q":316},{"start":13616,"end":13639,"p":41,"q":332},{"start":13640,"end":13658,"p":43,"q":317},{"start":13659,"end":13680,"p":37,"q":369},{"start":13681,"end":13704,"p":47,"q":291},{"start":13705,"end":13729,"p":31,"q":442},{"start":13730,"end":13754,"p":37,"q":371},{"start":13755,"end":13773,"p":29,"q":474},{"start":13774,"end":13798,"p":47,"q":293},{"start":13799,"end":13822,"p":31,"q":445},{"start":13823,"end":13845,"p":47,"q":294},{"start":13846,"end":13865,"p":37,"q":374},{"start":13866,"end":13892,"p":47,"q":295},{"start":13893,"end":13918,"p":29,"q":479},{"start":13919,"end":13939,"p":37,"q":376},{"start":13940,"end":13966,"p":53,"q":263},{"start":13967,"end":13986,"p":47,"q":297},{"start":13987,"end":14013,"p":37,"q":378},{"start":14014,"end":14039,"p":31,"q":452},{"start":14040,"end":14063,"p":29,"q":484},{"start":14064,"end":14090,"p":41,"q":343},{"start":14091,"end":14101,"p":31,"q":454},{"start":14102,"end":14127,"p":47,"q":300},{"start":14128,"end":14150,"p":29,"q":487},{"start":14151,"end":14174,"p":43,"q":329},{"start":14175,"end":14198,"p":37,"q":383},{"start":14199,"end":14225,"p":31,"q":458},{"start":14226,"end":14237,"p":29,"q":490},{"start":14238,"end":14260,"p":43,"q":331},{"start":14261,"end":14287,"p":31,"q":460},{"start":14288,"end":14309,"p":37,"q":386},{"start":14310,"end":14336,"p":41,"q":349},{"start":14337,"end":14362,"p":47,"q":305},{"start":14363,"end":14389,"p":43,"q":334},{"start":14390,"end":14411,"p":29,"q":496},{"start":14412,"end":14432,"p":43,"q":335},{"start":14433,"end":14459,"p":41,"q":352},{"start":14460,"end":14475,"p":43,"q":336},{"start":14476,"end":14500,"p":41,"q":353},{"start":14501,"end":14527,"p":29,"q":500},{"start":14528,"end":14550,"p":47,"q":309},{"start":14551,"end":14568,"p":37,"q":393},{"start":14569,"end":14585,"p":29,"q":502},{"start":14586,"end":14605,"p":37,"q":394},{"start":14606,"end":14628,"p":31,"q":471},{"start":14629,"end":14655,"p":53,"q":276},{"start":14656,"end":14679,"p":37,"q":396},{"start":14680,"end":14705,"p":41,"q":358},{"start":14706,"end":14730,"p":29,"q":507},{"start":14731,"end":14753,"p":37,"q":398},{"start":14754,"end":14776,"p":43,"q":343},{"start":14777,"end":14790,"p":37,"q":399},{"start":14791,"end":14817,"p":29,"q":510},{"start":14818,"end":14832,"p":47,"q":315},{"start":14833,"end":14846,"p":29,"q":511},{"start":14847,"end":14869,"p":41,"q":362},{"start":14870,"end":14879,"p":47,"q":316},{"start":14880,"end":14905,"p":43,"q":346},{"start":14906,"end":14926,"p":47,"q":317},{"start":14927,"end":14951,"p":41,"q":364},{"start":14952,"end":14975,"p":37,"q":404},{"start":14976,"end":15000,"p":31,"q":483},{"start":15001,"end":15026,"p":53,"q":283},{"start":15027,"end":15049,"p":29,"q":518},{"start":15050,"end":15074,"p":41,"q":367},{"start":15075,"end":15093,"p":31,"q":486},{"start":15094,"end":15120,"p":43,"q":351},{"start":15121,"end":15136,"p":29,"q":521},{"start":15137,"end":15163,"p":43,"q":352},{"start":15164,"end":15186,"p":31,"q":489},{"start":15187,"end":15208,"p":47,"q":323},{"start":15209,"end":15234,"p":37,"q":411},{"start":15235,"end":15255,"p":47,"q":324},{"start":15256,"end":15281,"p":29,"q":526},{"start":15282,"end":15308,"p":37,"q":413},{"start":15309,"end":15335,"p":43,"q":356},{"start":15336,"end":15361,"p":41,"q":374},{"start":15362,"end":15382,"p":37,"q":415},{"start":15383,"end":15403,"p":31,"q":496},{"start":15404,"end":15426,"p":29,"q":531},{"start":15427,"end":15450,"p":53,"q":291},{"start":15451,"end":15465,"p":31,"q":498},{"start":15466,"end":15490,"p":47,"q":329},{"start":15491,"end":15513,"p":29,"q":534},{"start":15514,"end":15537,"p":47,"q":330},{"start":15538,"end":15558,"p":31,"q":501},{"start":15559,"end":15584,"p":47,"q":331},{"start":15585,"end":15609,"p":53,"q":294},{"start":15610,"end":15636,"p":43,"q":363},{"start":15637,"end":15662,"p":53,"q":295},{"start":15663,"end":15689,"p":41,"q":382},{"start":15690,"end":15716,"p":29,"q":541},{"start":15717,"end":15730,"p":41,"q":383},{"start":15731,"end":15752,"p":37,"q":425},{"start":15753,"end":15775,"p":31,"q":508},{"start":15776,"end":15789,"p":37,"q":426},{"start":15790,"end":15812,"p":41,"q":385},{"start":15813,"end":15837,"p":31,"q":510},{"start":15838,"end":15863,"p":37,"q":428},{"start":15864,"end":15890,"p":29,"q":547},{"start":15891,"end":15913,"p":47,"q":338},{"start":15914,"end":15937,"p":37,"q":430},{"start":15938,"end":15961,"p":31,"q":514},{"start":15962,"end":15980,"p":43,"q":371},{"start":15981,"end":16007,"p":47,"q":340},{"start":16008,"end":16033,"p":53,"q":302},{"start":16034,"end":16058,"p":41,"q":391},{"start":16059,"end":16085,"p":31,"q":518},{"start":16086,"end":16109,"p":43,"q":374},{"start":16110,"end":16122,"p":29,"q":555},{"start":16123,"end":16148,"p":47,"q":343},{"start":16149,"end":16159,"p":37,"q":436},{"start":16160,"end":16181,"p":41,"q":394},{"start":16182,"end":16196,"p":37,"q":437},{"start":16197,"end":16222,"p":41,"q":395},{"start":16223,"end":16245,"p":53,"q":306},{"start":16246,"end":16271,"p":31,"q":524},{"start":16272,"end":16298,"p":53,"q":307},{"start":16299,"end":16325,"p":29,"q":562},{"start":16326,"end":16351,"p":53,"q":308},{"start":16352,"end":16367,"p":43,"q":380},{"start":16368,"end":16386,"p":41,"q":399},{"start":16387,"end":16412,"p":29,"q":565},{"start":16413,"end":16430,"p":47,"q":349},{"start":16431,"end":16457,"p":31,"q":530},{"start":16458,"end":16477,"p":47,"q":350},{"start":16478,"end":16499,"p":29,"q":568},{"start":16500,"end":16524,"p":47,"q":351},{"start":16525,"end":16550,"p":31,"q":533},{"start":16551,"end":16571,"p":47,"q":352},{"start":16572,"end":16591,"p":41,"q":404},{"start":16592,"end":16618,"p":47,"q":353},{"start":16619,"end":16644,"p":29,"q":573},{"start":16645,"end":16669,"p":53,"q":314},{"start":16670,"end":16677,"p":37,"q":450},{"start":16678,"end":16702,"p":29,"q":575},{"start":16703,"end":16722,"p":53,"q":315},{"start":16723,"end":16736,"p":31,"q":539},{"start":16737,"end":16760,"p":29,"q":577},{"start":16761,"end":16775,"p":53,"q":316},{"start":16776,"end":16798,"p":31,"q":541},{"start":16799,"end":16825,"p":37,"q":454},{"start":16826,"end":16847,"p":29,"q":580},{"start":16848,"end":16862,"p":37,"q":455},{"start":16863,"end":16883,"p":43,"q":392},{"start":16884,"end":16905,"p":29,"q":582},{"start":16906,"end":16926,"p":43,"q":393},{"start":16927,"end":16953,"p":31,"q":546},{"start":16954,"end":16973,"p":37,"q":458},{"start":16974,"end":16994,"p":47,"q":361},{"start":16995,"end":17021,"p":29,"q":586},{"start":17022,"end":17047,"p":37,"q":460},{"start":17048,"end":17055,"p":43,"q":396},{"start":17056,"end":17079,"p":29,"q":588},{"start":17080,"end":17098,"p":43,"q":397},{"start":17099,"end":17124,"p":41,"q":417},{"start":17125,"end":17146,"p":53,"q":323},{"start":17147,"end":17170,"p":31,"q":553},{"start":17171,"end":17195,"p":29,"q":592},{"start":17196,"end":17206,"p":41,"q":419},{"start":17207,"end":17232,"p":31,"q":555},{"start":17233,"end":17253,"p":29,"q":594},{"start":17254,"end":17276,"p":47,"q":367},{"start":17277,"end":17294,"p":31,"q":557},{"start":17295,"end":17313,"p":43,"q":402},{"start":17314,"end":17340,"p":29,"q":597},{"start":17341,"end":17358,"p":53,"q":327},{"start":17359,"end":17380,"p":37,"q":469},{"start":17381,"end":17399,"p":43,"q":404},{"start":17400,"end":17418,"p":31,"q":561},{"start":17419,"end":17442,"p":43,"q":405},{"start":17443,"end":17464,"p":47,"q":371},{"start":17465,"end":17491,"p":37,"q":472},{"start":17492,"end":17517,"p":53,"q":330},{"start":17518,"end":17543,"p":29,"q":604},{"start":17544,"end":17570,"p":53,"q":331},{"start":17571,"end":17575,"p":41,"q":428},{"start":17576,"end":17602,"p":37,"q":475},{"start":17603,"end":17623,"p":53,"q":332},{"start":17624,"end":17639,"p":37,"q":476},{"start":17640,"end":17666,"p":31,"q":569},{"start":17667,"end":17688,"p":29,"q":609},{"start":17689,"end":17713,"p":37,"q":478},{"start":17714,"end":17739,"p":41,"q":432},{"start":17740,"end":17759,"p":31,"q":572},{"start":17760,"end":17786,"p":43,"q":413},{"start":17787,"end":17804,"p":29,"q":613},{"start":17805,"end":17829,"p":43,"q":414},{"start":17830,"end":17852,"p":31,"q":575},{"start":17853,"end":17872,"p":43,"q":415},{"start":17873,"end":17898,"p":37,"q":483},{"start":17899,"end":17920,"p":29,"q":617},{"start":17921,"end":17945,"p":31,"q":578},{"start":17946,"end":17972,"p":37,"q":485},{"start":17973,"end":17994,"p":53,"q":339},{"start":17995,"end":18009,"p":37,"q":486},{"start":18010,"end":18036,"p":29,"q":621},{"start":18037,"end":18047,"p":53,"q":340},{"start":18048,"end":18069,"p":31,"q":582},{"start":18070,"end":18094,"p":29,"q":623},{"start":18095,"end":18120,"p":37,"q":489},{"start":18121,"end":18131,"p":31,"q":584},{"start":18132,"end":18157,"p":37,"q":490},{"start":18158,"end":18181,"p":29,"q":626},{"start":18182,"end":18206,"p":53,"q":343},{"start":18207,"end":18231,"p":37,"q":492},{"start":18232,"end":18255,"p":31,"q":588},{"start":18256,"end":18272,"p":41,"q":445},{"start":18273,"end":18297,"p":29,"q":630},{"start":18298,"end":18317,"p":31,"q":590},{"start":18318,"end":18342,"p":37,"q":495},{"start":18343,"end":18365,"p":53,"q":346},{"start":18366,"end":18388,"p":43,"q":427},{"start":18389,"end":18413,"p":29,"q":634},{"start":18414,"end":18436,"p":41,"q":449},{"start":18437,"end":18453,"p":37,"q":498},{"start":18454,"end":18477,"p":41,"q":450},{"start":18478,"end":18503,"p":31,"q":596},{"start":18504,"end":18529,"p":29,"q":638},{"start":18530,"end":18545,"p":47,"q":394},{"start":18546,"end":18565,"p":31,"q":598},{"start":18566,"end":18592,"p":47,"q":395},{"start":18593,"end":18616,"p":29,"q":641},{"start":18617,"end":18641,"p":41,"q":454},{"start":18642,"end":18658,"p":31,"q":601},{"start":18659,"end":18683,"p":53,"q":352},{"start":18684,"end":18703,"p":29,"q":644},{"start":18704,"end":18723,"p":41,"q":456},{"start":18724,"end":18749,"p":37,"q":506},{"start":18750,"end":18775,"p":43,"q":436},{"start":18776,"end":18790,"p":29,"q":647},{"start":18791,"end":18813,"p":31,"q":606},{"start":18814,"end":18827,"p":47,"q":400},{"start":18828,"end":18848,"p":29,"q":649},{"start":18849,"end":18875,"p":31,"q":608},{"start":18876,"end":18897,"p":37,"q":510},{"start":18898,"end":18921,"p":47,"q":402},{"start":18922,"end":18948,"p":53,"q":357},{"start":18949,"end":18971,"p":37,"q":512},{"start":18972,"end":18993,"p":29,"q":654},{"start":18994,"end":19015,"p":47,"q":404},{"start":19016,"end":19033,"p":43,"q":442},{"start":19034,"end":19054,"p":53,"q":359},{"start":19055,"end":19080,"p":29,"q":657},{"start":19081,"end":19107,"p":53,"q":360},{"start":19108,"end":19133,"p":41,"q":466},{"start":19134,"end":19160,"p":53,"q":361},{"start":19161,"end":19185,"p":31,"q":618},{"start":19186,"end":19205,"p":43,"q":446},{"start":19206,"end":19230,"p":37,"q":519},{"start":19231,"end":19256,"p":41,"q":469},{"start":19257,"end":19283,"p":29,"q":664},{"start":19284,"end":19309,"p":31,"q":622},{"start":19310,"end":19334,"p":43,"q":449},{"start":19335,"end":19344,"p":47,"q":411},{"start":19345,"end":19371,"p":31,"q":624},{"start":19372,"end":19391,"p":47,"q":412},{"start":19392,"end":19415,"p":37,"q":524},{"start":19416,"end":19438,"p":47,"q":413},{"start":19439,"end":19464,"p":31,"q":627},{"start":19465,"end":19489,"p":37,"q":526},{"start":19490,"end":19515,"p":29,"q":672},{"start":19516,"end":19532,"p":47,"q":415},{"start":19533,"end":19557,"p":31,"q":630},{"start":19558,"end":19584,"p":41,"q":477},{"start":19585,"end":19602,"p":29,"q":675},{"start":19603,"end":19626,"p":47,"q":417},{"start":19627,"end":19650,"p":31,"q":633},{"start":19651,"end":19674,"p":37,"q":531},{"start":19675,"end":19690,"p":53,"q":371},{"start":19691,"end":19712,"p":31,"q":635},{"start":19713,"end":19721,"p":43,"q":458},{"start":19722,"end":19748,"p":37,"q":533},{"start":19749,"end":19774,"p":31,"q":637},{"start":19775,"end":19796,"p":53,"q":373},{"start":19797,"end":19822,"p":37,"q":535},{"start":19823,"end":19849,"p":53,"q":374},{"start":19850,"end":19871,"p":41,"q":484},{"start":19872,"end":19898,"p":31,"q":641},{"start":19899,"end":19921,"p":29,"q":686},{"start":19922,"end":19936,"p":43,"q":463},{"start":19937,"end":19960,"p":31,"q":643},{"start":19961,"end":19979,"p":29,"q":688},{"start":19980,"end":20002,"p":47,"q":425},{"start":20003,"end":20022,"p":31,"q":645},{"start":20023,"end":20049,"p":47,"q":426},{"start":20050,"end":20076,"p":41,"q":489},{"start":20077,"end":20096,"p":47,"q":427},{"start":20097,"end":20118,"p":37,"q":543},{"start":20119,"end":20143,"p":47,"q":428},{"start":20144,"end":20167,"p":53,"q":380},{"start":20168,"end":20194,"p":43,"q":469},{"start":20195,"end":20220,"p":53,"q":381},{"start":20221,"end":20240,"p":29,"q":697},{"start":20241,"end":20266,"p":37,"q":547},{"start":20267,"end":20284,"p":47,"q":431},{"start":20285,"end":20303,"p":37,"q":548},{"start":20304,"end":20327,"p":29,"q":700},{"start":20328,"end":20340,"p":37,"q":549},{"start":20341,"end":20366,"p":43,"q":473},{"start":20367,"end":20385,"p":29,"q":702},{"start":20386,"end":20409,"p":43,"q":474},{"start":20410,"end":20432,"p":53,"q":385},{"start":20433,"end":20456,"p":31,"q":659},{"start":20457,"end":20472,"p":29,"q":705},{"start":20473,"end":20495,"p":43,"q":476},{"start":20496,"end":20519,"p":47,"q":436},{"start":20520,"end":20538,"p":43,"q":477},{"start":20539,"end":20562,"p":37,"q":555},{"start":20563,"end":20588,"p":29,"q":709},{"start":20589,"end":20613,"p":47,"q":438},{"start":20614,"end":20636,"p":37,"q":557},{"start":20637,"end":20660,"p":47,"q":439},{"start":20661,"end":20675,"p":29,"q":712},{"start":20676,"end":20697,"p":53,"q":390},{"start":20698,"end":20710,"p":37,"q":559},{"start":20711,"end":20735,"p":31,"q":668},{"start":20736,"end":20762,"p":29,"q":715},{"start":20763,"end":20784,"p":37,"q":561},{"start":20785,"end":20803,"p":53,"q":392},{"start":20804,"end":20828,"p":31,"q":671},{"start":20829,"end":20855,"p":41,"q":508},{"start":20856,"end":20882,"p":43,"q":485},{"start":20883,"end":20909,"p":53,"q":394},{"start":20910,"end":20936,"p":29,"q":721},{"start":20937,"end":20962,"p":53,"q":395},{"start":20963,"end":20989,"p":47,"q":446},{"start":20990,"end":21015,"p":53,"q":396},{"start":21016,"end":21036,"p":47,"q":447},{"start":21037,"end":21060,"p":41,"q":513},{"start":21061,"end":21083,"p":47,"q":448},{"start":21084,"end":21110,"p":29,"q":727},{"start":21111,"end":21130,"p":47,"q":449},{"start":21131,"end":21154,"p":37,"q":571},{"start":21155,"end":21177,"p":47,"q":450},{"start":21178,"end":21200,"p":31,"q":683},{"start":21201,"end":21227,"p":53,"q":400},{"start":21228,"end":21231,"p":31,"q":684},{"start":21232,"end":21255,"p":29,"q":732},{"start":21256,"end":21280,"p":53,"q":401},{"start":21281,"end":21306,"p":41,"q":519},{"start":21307,"end":21333,"p":53,"q":402},{"start":21334,"end":21355,"p":31,"q":688},{"start":21356,"end":21376,"p":37,"q":577},{"start":21377,"end":21400,"p":29,"q":737},{"start":21401,"end":21417,"p":31,"q":690},{"start":21418,"end":21441,"p":43,"q":498},{"start":21442,"end":21459,"p":47,"q":456},{"start":21460,"end":21484,"p":43,"q":499},{"start":21485,"end":21511,"p":41,"q":524},{"start":21512,"end":21527,"p":43,"q":500},{"start":21528,"end":21553,"p":47,"q":458},{"start":21554,"end":21574,"p":29,"q":743},{"start":21575,"end":21600,"p":47,"q":459},{"start":21601,"end":21613,"p":43,"q":502},{"start":21614,"end":21635,"p":37,"q":584},{"start":21636,"end":21661,"p":29,"q":746},{"start":21662,"end":21675,"p":41,"q":528},{"start":21676,"end":21699,"p":43,"q":504},{"start":21700,"end":21719,"p":29,"q":748},{"start":21720,"end":21746,"p":37,"q":587},{"start":21747,"end":21758,"p":31,"q":701},{"start":21759,"end":21785,"p":43,"q":506},{"start":21786,"end":21810,"p":53,"q":411},{"start":21811,"end":21835,"p":29,"q":752},{"start":21836,"end":21857,"p":37,"q":590},{"start":21858,"end":21882,"p":31,"q":705},{"start":21883,"end":21894,"p":37,"q":591},{"start":21895,"end":21921,"p":41,"q":534},{"start":21922,"end":21944,"p":31,"q":707},{"start":21945,"end":21969,"p":53,"q":414},{"start":21970,"end":21980,"p":29,"q":757},{"start":21981,"end":22006,"p":31,"q":709},{"start":22007,"end":22023,"p":47,"q":468},{"start":22024,"end":22044,"p":41,"q":537},{"start":22045,"end":22070,"p":47,"q":469},{"start":22071,"end":22096,"p":29,"q":761},{"start":22097,"end":22117,"p":47,"q":470},{"start":22118,"end":22130,"p":31,"q":713},{"start":22131,"end":22154,"p":29,"q":763},{"start":22155,"end":22181,"p":53,"q":418},{"start":22182,"end":22208,"p":41,"q":541},{"start":22209,"end":22234,"p":53,"q":419},{"start":22235,"end":22258,"p":43,"q":517},{"start":22259,"end":22285,"p":31,"q":718},{"start":22286,"end":22305,"p":47,"q":474},{"start":22306,"end":22331,"p":41,"q":544},{"start":22332,"end":22357,"p":29,"q":770},{"start":22358,"end":22378,"p":31,"q":721},{"start":22379,"end":22399,"p":47,"q":476},{"start":22400,"end":22415,"p":29,"q":772},{"start":22416,"end":22440,"p":31,"q":723},{"start":22441,"end":22454,"p":41,"q":547},{"start":22455,"end":22473,"p":29,"q":774},{"start":22474,"end":22499,"p":53,"q":424},{"start":22500,"end":22523,"p":37,"q":608},{"start":22524,"end":22540,"p":47,"q":479},{"start":22541,"end":22564,"p":31,"q":727},{"start":22565,"end":22589,"p":29,"q":778},{"start":22590,"end":22605,"p":53,"q":426},{"start":22606,"end":22626,"p":31,"q":729},{"start":22627,"end":22647,"p":29,"q":780},{"start":22648,"end":22671,"p":37,"q":612},{"start":22672,"end":22688,"p":31,"q":731},{"start":22689,"end":22711,"p":53,"q":428},{"start":22712,"end":22734,"p":29,"q":783},{"start":22735,"end":22750,"p":31,"q":733},{"start":22751,"end":22775,"p":47,"q":484},{"start":22776,"end":22792,"p":29,"q":785},{"start":22793,"end":22819,"p":37,"q":616},{"start":22820,"end":22843,"p":31,"q":736},{"start":22844,"end":22870,"p":53,"q":431},{"start":22871,"end":22893,"p":37,"q":618},{"start":22894,"end":22916,"p":47,"q":487},{"start":22917,"end":22937,"p":29,"q":790},{"start":22938,"end":22963,"p":47,"q":488},{"start":22964,"end":22989,"p":43,"q":534},{"start":22990,"end":23010,"p":47,"q":489},{"start":23011,"end":23032,"p":43,"q":535},{"start":23033,"end":23057,"p":47,"q":490},{"start":23058,"end":23082,"p":29,"q":795},{"start":23083,"end":23104,"p":47,"q":491},{"start":23105,"end":23122,"p":31,"q":745},{"start":23123,"end":23140,"p":29,"q":797},{"start":23141,"end":23161,"p":43,"q":538},{"start":23162,"end":23188,"p":53,"q":437},{"start":23189,"end":23215,"p":31,"q":748},{"start":23216,"end":23241,"p":53,"q":438},{"start":23242,"end":23263,"p":37,"q":628},{"start":23264,"end":23290,"p":43,"q":541},{"start":23291,"end":23315,"p":41,"q":568},{"start":23316,"end":23339,"p":31,"q":752},{"start":23340,"end":23356,"p":41,"q":569},{"start":23357,"end":23376,"p":43,"q":543},{"start":23377,"end":23401,"p":29,"q":806},{"start":23402,"end":23419,"p":43,"q":544},{"start":23420,"end":23438,"p":41,"q":571},{"start":23439,"end":23463,"p":31,"q":756},{"start":23464,"end":23488,"p":29,"q":809},{"start":23489,"end":23506,"p":53,"q":443},{"start":23507,"end":23527,"p":47,"q":500},{"start":23528,"end":23548,"p":43,"q":547},{"start":23549,"end":23575,"p":29,"q":812},{"start":23576,"end":23602,"p":41,"q":575},{"start":23603,"end":23621,"p":47,"q":502},{"start":23622,"end":23643,"p":41,"q":576},{"start":23644,"end":23670,"p":37,"q":639},{"start":23671,"end":23691,"p":29,"q":816},{"start":23692,"end":23718,"p":53,"q":447},{"start":23719,"end":23744,"p":37,"q":641},{"start":23745,"end":23771,"p":53,"q":448},{"start":23772,"end":23781,"p":37,"q":642},{"start":23782,"end":23807,"p":29,"q":820},{"start":23808,"end":23824,"p":53,"q":449},{"start":23825,"end":23849,"p":43,"q":554},{"start":23850,"end":23866,"p":31,"q":769},{"start":23867,"end":23892,"p":37,"q":645},{"start":23893,"end":23903,"p":47,"q":508},{"start":23904,"end":23930,"p":41,"q":583},{"start":23931,"end":23952,"p":29,"q":825},{"start":23953,"end":23978,"p":43,"q":557},{"start":23979,"end":24003,"p":37,"q":648},{"start":24004,"end":24021,"p":31,"q":774},{"start":24022,"end":24044,"p":47,"q":511},{"start":24045,"end":24068,"p":29,"q":829},{"start":24069,"end":24094,"p":41,"q":587},{"start":24095,"end":24114,"p":31,"q":777},{"start":24115,"end":24138,"p":47,"q":513},{"start":24139,"end":24155,"p":29,"q":832},{"start":24156,"end":24176,"p":31,"q":779},{"start":24177,"end":24195,"p":53,"q":456},{"start":24196,"end":24217,"p":41,"q":590},{"start":24218,"end":24242,"p":29,"q":835},{"start":24243,"end":24269,"p":31,"q":782},{"start":24270,"end":24279,"p":43,"q":564},{"start":24280,"end":24301,"p":53,"q":458},{"start":24302,"end":24326,"p":47,"q":517},{"start":24327,"end":24340,"p":41,"q":593},{"start":24341,"end":24365,"p":43,"q":566},{"start":24366,"end":24387,"p":29,"q":840},{"start":24388,"end":24410,"p":37,"q":659},{"start":24411,"end":24424,"p":31,"q":787},{"start":24425,"end":24451,"p":43,"q":568},{"start":24452,"end":24474,"p":29,"q":843},{"start":24475,"end":24494,"p":43,"q":569},{"start":24495,"end":24521,"p":37,"q":662},{"start":24522,"end":24548,"p":31,"q":791},{"start":24549,"end":24566,"p":53,"q":463},{"start":24567,"end":24590,"p":29,"q":847},{"start":24591,"end":24610,"p":31,"q":793},{"start":24611,"end":24632,"p":37,"q":665},{"start":24633,"end":24655,"p":47,"q":524},{"start":24656,"end":24677,"p":29,"q":850},{"start":24678,"end":24703,"p":31,"q":796},{"start":24704,"end":24725,"p":53,"q":466},{"start":24726,"end":24752,"p":43,"q":575},{"start":24753,"end":24778,"p":53,"q":467},{"start":24779,"end":24796,"p":31,"q":799},{"start":24797,"end":24822,"p":29,"q":855},{"start":24823,"end":24843,"p":47,"q":528},{"start":24844,"end":24858,"p":31,"q":801},{"start":24859,"end":24884,"p":53,"q":469},{"start":24885,"end":24909,"p":29,"q":858},{"start":24910,"end":24928,"p":37,"q":673},{"start":24929,"end":24955,"p":41,"q":608},{"start":24956,"end":24982,"p":31,"q":805},{"start":24983,"end":25002,"p":37,"q":675},{"start":25003,"end":25025,"p":29,"q":862},{"start":25026,"end":25044,"p":31,"q":807},{"start":25045,"end":25054,"p":29,"q":863},{"start":25055,"end":25078,"p":41,"q":611},{"start":25079,"end":25096,"p":43,"q":583},{"start":25097,"end":25119,"p":41,"q":612},{"start":25120,"end":25141,"p":29,"q":866},{"start":25142,"end":25168,"p":31,"q":811},{"start":25169,"end":25187,"p":37,"q":680},{"start":25188,"end":25202,"p":53,"q":475},{"start":25203,"end":25228,"p":29,"q":869},{"start":25229,"end":25255,"p":53,"q":476},{"start":25256,"end":25268,"p":43,"q":587},{"start":25269,"end":25292,"p":31,"q":815},{"start":25293,"end":25315,"p":29,"q":872},{"start":25316,"end":25335,"p":37,"q":684},{"start":25336,"end":25361,"p":53,"q":478},{"start":25362,"end":25385,"p":31,"q":818},{"start":25386,"end":25409,"p":37,"q":686},{"start":25410,"end":25431,"p":29,"q":876},{"start":25432,"end":25454,"p":47,"q":541},{"start":25455,"end":25478,"p":31,"q":821},{"start":25479,"end":25501,"p":47,"q":542},{"start":25502,"end":25526,"p":43,"q":593},{"start":25527,"end":25548,"p":47,"q":543},{"start":25549,"end":25573,"p":53,"q":482},{"start":25574,"end":25595,"p":47,"q":544},{"start":25596,"end":25612,"p":43,"q":595},{"start":25613,"end":25634,"p":29,"q":883},{"start":25635,"end":25655,"p":43,"q":596},{"start":25656,"end":25679,"p":53,"q":484},{"start":25680,"end":25705,"p":37,"q":694},{"start":25706,"end":25732,"p":53,"q":485},{"start":25733,"end":25757,"p":31,"q":830},{"start":25758,"end":25784,"p":43,"q":599},{"start":25785,"end":25808,"p":29,"q":889},{"start":25809,"end":25830,"p":47,"q":549},{"start":25831,"end":25857,"p":41,"q":630},{"start":25858,"end":25881,"p":31,"q":834},{"start":25882,"end":25898,"p":41,"q":631},{"start":25899,"end":25924,"p":29,"q":893},{"start":25925,"end":25944,"p":53,"q":489},{"start":25945,"end":25971,"p":47,"q":552},{"start":25972,"end":25997,"p":53,"q":490},{"start":25998,"end":26021,"p":41,"q":634},{"start":26022,"end":26042,"p":43,"q":605},{"start":26043,"end":26069,"p":29,"q":898},{"start":26070,"end":26085,"p":43,"q":606},{"start":26086,"end":26112,"p":37,"q":705},{"start":26113,"end":26129,"p":31,"q":842},{"start":26130,"end":26156,"p":29,"q":901},{"start":26157,"end":26171,"p":43,"q":608},{"start":26172,"end":26191,"p":31,"q":844},{"start":26192,"end":26214,"p":29,"q":903},{"start":26215,"end":26226,"p":41,"q":639},{"start":26227,"end":26253,"p":31,"q":846},{"start":26254,"end":26272,"p":29,"q":905},{"start":26273,"end":26297,"p":37,"q":710},{"start":26298,"end":26315,"p":31,"q":848},{"start":26316,"end":26334,"p":37,"q":711},{"start":26335,"end":26359,"p":29,"q":908},{"start":26360,"end":26386,"p":43,"q":613},{"start":26387,"end":26408,"p":31,"q":851},{"start":26409,"end":26431,"p":41,"q":644},{"start":26432,"end":26446,"p":29,"q":911},{"start":26447,"end":26472,"p":41,"q":645},{"start":26473,"end":26488,"p":47,"q":563},{"start":26489,"end":26515,"p":43,"q":616},{"start":26516,"end":26535,"p":47,"q":564},{"start":26536,"end":26562,"p":29,"q":915},{"start":26563,"end":26582,"p":47,"q":565},{"start":26583,"end":26601,"p":43,"q":618},{"start":26602,"end":26625,"p":31,"q":858},{"start":26626,"end":26649,"p":29,"q":918},{"start":26650,"end":26676,"p":47,"q":567},{"start":26677,"end":26687,"p":31,"q":860},{"start":26688,"end":26707,"p":29,"q":920},{"start":26708,"end":26730,"p":43,"q":621},{"start":26731,"end":26749,"p":31,"q":862},{"start":26750,"end":26773,"p":43,"q":622},{"start":26774,"end":26800,"p":41,"q":653},{"start":26801,"end":26823,"p":29,"q":924},{"start":26824,"end":26845,"p":53,"q":506},{"start":26846,"end":26864,"p":47,"q":571},{"start":26865,"end":26889,"p":37,"q":726},{"start":26890,"end":26911,"p":47,"q":572},{"start":26912,"end":26935,"p":31,"q":868},{"start":26936,"end":26958,"p":47,"q":573},{"start":26959,"end":26968,"p":29,"q":929},{"start":26969,"end":26988,"p":43,"q":627},{"start":26989,"end":27005,"p":41,"q":658},{"start":27006,"end":27031,"p":43,"q":628},{"start":27032,"end":27057,"p":53,"q":510},{"start":27058,"end":27084,"p":29,"q":933},{"start":27085,"end":27111,"p":37,"q":732},{"start":27112,"end":27128,"p":41,"q":661},{"start":27129,"end":27152,"p":31,"q":875},{"start":27153,"end":27171,"p":29,"q":936},{"start":27172,"end":27193,"p":47,"q":578},{"start":27194,"end":27216,"p":53,"q":513},{"start":27217,"end":27240,"p":47,"q":579},{"start":27241,"end":27259,"p":37,"q":736},{"start":27260,"end":27276,"p":31,"q":879},{"start":27277,"end":27296,"p":37,"q":737},{"start":27297,"end":27322,"p":53,"q":515},{"start":27323,"end":27345,"p":29,"q":942},{"start":27346,"end":27370,"p":37,"q":739},{"start":27371,"end":27381,"p":47,"q":582},{"start":27382,"end":27407,"p":37,"q":740},{"start":27408,"end":27432,"p":29,"q":945},{"start":27433,"end":27456,"p":41,"q":669},{"start":27457,"end":27481,"p":37,"q":742},{"start":27482,"end":27504,"p":43,"q":639},{"start":27505,"end":27524,"p":31,"q":887},{"start":27525,"end":27548,"p":29,"q":949},{"start":27549,"end":27569,"p":47,"q":586},{"start":27570,"end":27592,"p":37,"q":745},{"start":27593,"end":27617,"p":31,"q":890},{"start":27618,"end":27640,"p":53,"q":521},{"start":27641,"end":27666,"p":37,"q":747},{"start":27667,"end":27693,"p":29,"q":954},{"start":27694,"end":27719,"p":43,"q":644},{"start":27720,"end":27746,"p":53,"q":523},{"start":27747,"end":27772,"p":31,"q":895},{"start":27773,"end":27799,"p":53,"q":524},{"start":27800,"end":27825,"p":41,"q":678},{"start":27826,"end":27852,"p":53,"q":525},{"start":27853,"end":27867,"p":29,"q":960},{"start":27868,"end":27891,"p":43,"q":648},{"start":27892,"end":27907,"p":41,"q":680},{"start":27908,"end":27934,"p":43,"q":649},{"start":27935,"end":27958,"p":31,"q":901},{"start":27959,"end":27983,"p":29,"q":964},{"start":27984,"end":27999,"p":37,"q":756},{"start":28000,"end":28020,"p":31,"q":903},{"start":28021,"end":28041,"p":29,"q":966},{"start":28042,"end":28064,"p":53,"q":529},{"start":28065,"end":28086,"p":47,"q":597},{"start":28087,"end":28113,"p":31,"q":906},{"start":28114,"end":28133,"p":47,"q":598},{"start":28134,"end":28157,"p":29,"q":970},{"start":28158,"end":28184,"p":37,"q":761},{"start":28185,"end":28206,"p":31,"q":909},{"start":28207,"end":28227,"p":47,"q":600},{"start":28228,"end":28244,"p":29,"q":973},{"start":28245,"end":28268,"p":31,"q":911},{"start":28269,"end":28295,"p":37,"q":764},{"start":28296,"end":28321,"p":43,"q":658},{"start":28322,"end":28332,"p":37,"q":765},{"start":28333,"end":28358,"p":41,"q":691},{"start":28359,"end":28382,"p":53,"q":535},{"start":28383,"end":28407,"p":43,"q":660},{"start":28408,"end":28423,"p":31,"q":916},{"start":28424,"end":28450,"p":43,"q":661},{"start":28451,"end":28476,"p":29,"q":981},{"start":28477,"end":28493,"p":43,"q":662},{"start":28494,"end":28517,"p":37,"q":770},{"start":28518,"end":28541,"p":53,"q":538},{"start":28542,"end":28563,"p":29,"q":984},{"start":28564,"end":28579,"p":43,"q":664},{"start":28580,"end":28604,"p":41,"q":697},{"start":28605,"end":28628,"p":37,"q":773},{"start":28629,"end":28650,"p":29,"q":987},{"start":28651,"end":28671,"p":31,"q":924},{"start":28672,"end":28697,"p":47,"q":610},{"start":28698,"end":28708,"p":29,"q":989},{"start":28709,"end":28733,"p":31,"q":926},{"start":28734,"end":28753,"p":53,"q":542},{"start":28754,"end":28776,"p":37,"q":777},{"start":28777,"end":28795,"p":29,"q":992},{"start":28796,"end":28813,"p":37,"q":778},{"start":28814,"end":28838,"p":47,"q":613},{"start":28839,"end":28859,"p":53,"q":544},{"start":28860,"end":28885,"p":47,"q":614},{"start":28886,"end":28912,"p":53,"q":545},{"start":28913,"end":28932,"p":41,"q":705},{"start":28933,"end":28950,"p":31,"q":933},{"start":28951,"end":28973,"p":41,"q":706},{"start":28974,"end":28998,"p":29,"q":999},{"start":28999,"end":29018,"p":53,"q":547},{"start":29019,"end":29043,"p":31,"q":936},{"start":29044,"end":29056,"p":29,"q":1001},{"start":29057,"end":29074,"p":31,"q":937},{"start":29075,"end":29096,"p":41,"q":709},{"start":29097,"end":29120,"p":47,"q":619},{"start":29121,"end":29146,"p":37,"q":787},{"start":29147,"end":29172,"p":29,"q":1005},{"start":29173,"end":29198,"p":31,"q":941},{"start":29199,"end":29224,"p":43,"q":679},{"start":29225,"end":29230,"p":29,"q":1007},{"start":29231,"end":29257,"p":37,"q":790},{"start":29258,"end":29283,"p":53,"q":552},{"start":29284,"end":29310,"p":43,"q":681},{"start":29311,"end":29336,"p":53,"q":553},{"start":29337,"end":29355,"p":47,"q":624},{"start":29356,"end":29375,"p":29,"q":1012},{"start":29376,"end":29402,"p":47,"q":625},{"start":29403,"end":29424,"p":41,"q":717},{"start":29425,"end":29449,"p":47,"q":626},{"start":29450,"end":29465,"p":41,"q":718},{"start":29466,"end":29491,"p":29,"q":1016},{"start":29492,"end":29516,"p":37,"q":797},{"start":29517,"end":29543,"p":47,"q":628},{"start":29544,"end":29570,"p":31,"q":953},{"start":29571,"end":29590,"p":37,"q":799},{"start":29591,"end":29611,"p":43,"q":688},{"start":29612,"end":29637,"p":47,"q":630},{"start":29638,"end":29664,"p":37,"q":801},{"start":29665,"end":29684,"p":47,"q":631},{"start":29685,"end":29711,"p":41,"q":724},{"start":29712,"end":29738,"p":37,"q":803},{"start":29739,"end":29760,"p":53,"q":561},{"start":29761,"end":29787,"p":31,"q":960},{"start":29788,"end":29813,"p":53,"q":562},{"start":29814,"end":29839,"p":29,"q":1028},{"start":29840,"end":29866,"p":53,"q":563},{"start":29867,"end":29886,"p":37,"q":807},{"start":29887,"end":29912,"p":43,"q":695},{"start":29913,"end":29926,"p":29,"q":1031},{"start":29927,"end":29942,"p":31,"q":965},{"start":29943,"end":29966,"p":47,"q":637},{"start":29967,"end":29984,"p":29,"q":1033},{"start":29985,"end":30004,"p":31,"q":967},{"start":30005,"end":30025,"p":53,"q":566},{"start":30026,"end":30042,"p":29,"q":1035},{"start":30043,"end":30066,"p":31,"q":969},{"start":30067,"end":30084,"p":43,"q":699},{"start":30085,"end":30108,"p":37,"q":813},{"start":30109,"end":30131,"p":53,"q":568},{"start":30132,"end":30158,"p":29,"q":1039},{"start":30159,"end":30184,"p":53,"q":569},{"start":30185,"end":30203,"p":41,"q":736},{"start":30204,"end":30221,"p":31,"q":974},{"start":30222,"end":30248,"p":47,"q":643},{"start":30249,"end":30274,"p":29,"q":1043},{"start":30275,"end":30299,"p":43,"q":704},{"start":30300,"end":30326,"p":41,"q":739},{"start":30327,"end":30345,"p":31,"q":978},{"start":30346,"end":30367,"p":37,"q":820},{"start":30368,"end":30390,"p":29,"q":1047},{"start":30391,"end":30408,"p":41,"q":741},{"start":30409,"end":30428,"p":43,"q":707},{"start":30429,"end":30449,"p":41,"q":742},{"start":30450,"end":30471,"p":43,"q":708},{"start":30472,"end":30490,"p":41,"q":743},{"start":30491,"end":30515,"p":37,"q":824},{"start":30516,"end":30535,"p":29,"q":1052},{"start":30536,"end":30562,"p":31,"q":985},{"start":30563,"end":30589,"p":37,"q":826},{"start":30590,"end":30613,"p":41,"q":746},{"start":30614,"end":30626,"p":37,"q":827},{"start":30627,"end":30651,"p":29,"q":1056},{"start":30652,"end":30671,"p":47,"q":652},{"start":30672,"end":30695,"p":41,"q":748},{"start":30696,"end":30718,"p":47,"q":653},{"start":30719,"end":30738,"p":29,"q":1059},{"start":30739,"end":30765,"p":47,"q":654},{"start":30766,"end":30779,"p":31,"q":992},{"start":30780,"end":30796,"p":29,"q":1061},{"start":30797,"end":30820,"p":53,"q":581},{"start":30821,"end":30841,"p":31,"q":994},{"start":30842,"end":30859,"p":41,"q":752},{"start":30860,"end":30885,"p":37,"q":834},{"start":30886,"end":30912,"p":29,"q":1065},{"start":30913,"end":30934,"p":31,"q":997},{"start":30935,"end":30959,"p":37,"q":836},{"start":30960,"end":30982,"p":41,"q":755},{"start":30983,"end":31000,"p":47,"q":659},{"start":31001,"end":31027,"p":31,"q":1000},{"start":31028,"end":31047,"p":47,"q":660},{"start":31048,"end":31073,"p":43,"q":722},{"start":31074,"end":31094,"p":47,"q":661},{"start":31095,"end":31120,"p":31,"q":1003},{"start":31121,"end":31146,"p":41,"q":759},{"start":31147,"end":31173,"p":29,"q":1074},{"start":31174,"end":31191,"p":53,"q":588},{"start":31192,"end":31218,"p":37,"q":843},{"start":31219,"end":31245,"p":43,"q":726},{"start":31246,"end":31269,"p":41,"q":762},{"start":31270,"end":31292,"p":37,"q":845},{"start":31293,"end":31318,"p":29,"q":1079},{"start":31319,"end":31337,"p":31,"q":1010},{"start":31338,"end":31351,"p":41,"q":764},{"start":31352,"end":31376,"p":29,"q":1081},{"start":31377,"end":31403,"p":37,"q":848},{"start":31404,"end":31430,"p":31,"q":1013},{"start":31431,"end":31456,"p":53,"q":593},{"start":31457,"end":31477,"p":37,"q":850},{"start":31478,"end":31503,"p":43,"q":732},{"start":31504,"end":31523,"p":31,"q":1016},{"start":31524,"end":31550,"p":29,"q":1087},{"start":31551,"end":31564,"p":47,"q":671},{"start":31565,"end":31589,"p":43,"q":734},{"start":31590,"end":31616,"p":31,"q":1019},{"start":31617,"end":31638,"p":41,"q":771},{"start":31639,"end":31662,"p":37,"q":855},{"start":31663,"end":31679,"p":41,"q":772},{"start":31680,"end":31705,"p":47,"q":674},{"start":31706,"end":31724,"p":29,"q":1093},{"start":31725,"end":31740,"p":31,"q":1023},{"start":31741,"end":31761,"p":41,"q":774},{"start":31762,"end":31782,"p":29,"q":1095},{"start":31783,"end":31804,"p":43,"q":739},{"start":31805,"end":31827,"p":53,"q":600},{"start":31828,"end":31847,"p":37,"q":860},{"start":31848,"end":31869,"p":29,"q":1098},{"start":31870,"end":31895,"p":31,"q":1028},{"start":31896,"end":31921,"p":37,"q":862},{"start":31922,"end":31940,"p":47,"q":679},{"start":31941,"end":31966,"p":41,"q":779},{"start":31967,"end":31988,"p":31,"q":1031},{"start":31989,"end":32014,"p":29,"q":1103},{"start":32015,"end":32039,"p":53,"q":604},{"start":32040,"end":32062,"p":43,"q":745},{"start":32063,"end":32089,"p":41,"q":782},{"start":32090,"end":32112,"p":31,"q":1035},{"start":32113,"end":32130,"p":29,"q":1107},{"start":32131,"end":32148,"p":43,"q":747},{"start":32149,"end":32175,"p":47,"q":684},{"start":32176,"end":32198,"p":53,"q":607},{"start":32199,"end":32222,"p":47,"q":685},{"start":32223,"end":32246,"p":29,"q":1111},{"start":32247,"end":32269,"p":47,"q":686},{"start":32270,"end":32294,"p":41,"q":787},{"start":32295,"end":32320,"p":43,"q":751},{"start":32321,"end":32335,"p":41,"q":788},{"start":32336,"end":32362,"p":29,"q":1115},{"start":32363,"end":32376,"p":41,"q":789},{"start":32377,"end":32402,"p":37,"q":875},{"start":32403,"end":32422,"p":31,"q":1045},{"start":32423,"end":32449,"p":29,"q":1118},{"start":32450,"end":32476,"p":37,"q":877},{"start":32477,"end":32499,"p":41,"q":792},{"start":32500,"end":32516,"p":53,"q":613},{"start":32517,"end":32540,"p":41,"q":793},{"start":32541,"end":32565,"p":29,"q":1122},{"start":32566,"end":32587,"p":37,"q":880},{"start":32588,"end":32608,"p":31,"q":1051},{"start":32609,"end":32624,"p":37,"q":881},{"start":32625,"end":32645,"p":47,"q":694},{"start":32646,"end":32670,"p":31,"q":1053},{"start":32671,"end":32692,"p":47,"q":695},{"start":32693,"end":32710,"p":29,"q":1127},{"start":32711,"end":32735,"p":37,"q":884},{"start":32736,"end":32750,"p":43,"q":761},{"start":32751,"end":32772,"p":37,"q":885},{"start":32773,"end":32797,"p":29,"q":1130},{"start":32798,"end":32809,"p":37,"q":886},{"start":32810,"end":32836,"p":43,"q":763},{"start":32837,"end":32856,"p":31,"q":1059},{"start":32857,"end":32883,"p":37,"q":888},{"start":32884,"end":32909,"p":41,"q":802},{"start":32910,"end":32927,"p":47,"q":700},{"start":32928,"end":32950,"p":41,"q":803},{"start":32951,"end":32974,"p":47,"q":701},{"start":32975,"end":33000,"p":29,"q":1137},{"start":33001,"end":33021,"p":47,"q":702},{"start":33022,"end":33046,"p":53,"q":623},{"start":33047,"end":33073,"p":31,"q":1066},{"start":33074,"end":33099,"p":53,"q":624},{"start":33100,"end":33116,"p":29,"q":1141},{"start":33117,"end":33142,"p":37,"q":895},{"start":33143,"end":33166,"p":31,"q":1069},{"start":33167,"end":33180,"p":43,"q":771},{"start":33181,"end":33205,"p":53,"q":626},{"start":33206,"end":33232,"p":29,"q":1145},{"start":33233,"end":33259,"p":31,"q":1072},{"start":33260,"end":33278,"p":41,"q":811},{"start":33279,"end":33303,"p":47,"q":708},{"start":33304,"end":33327,"p":37,"q":900},{"start":33328,"end":33352,"p":31,"q":1075},{"start":33353,"end":33377,"p":29,"q":1150},{"start":33378,"end":33401,"p":37,"q":902},{"start":33402,"end":33417,"p":53,"q":630},{"start":33418,"end":33444,"p":47,"q":711},{"start":33445,"end":33470,"p":53,"q":631},{"start":33471,"end":33493,"p":29,"q":1154},{"start":33494,"end":33512,"p":37,"q":905},{"start":33513,"end":33538,"p":31,"q":1081},{"start":33539,"end":33565,"p":41,"q":818},{"start":33566,"end":33586,"p":37,"q":907},{"start":33587,"end":33610,"p":43,"q":781},{"start":33611,"end":33632,"p":47,"q":715},{"start":33633,"end":33653,"p":43,"q":782},{"start":33654,"end":33679,"p":47,"q":716},{"start":33680,"end":33697,"p":37,"q":910},{"start":33698,"end":33724,"p":31,"q":1087},{"start":33725,"end":33739,"p":43,"q":784},{"start":33740,"end":33755,"p":31,"q":1088},{"start":33756,"end":33782,"p":43,"q":785},{"start":33783,"end":33808,"p":37,"q":913},{"start":33809,"end":33825,"p":43,"q":786},{"start":33826,"end":33852,"p":41,"q":825},{"start":33853,"end":33879,"p":31,"q":1092},{"start":33880,"end":33899,"p":29,"q":1168},{"start":33900,"end":33919,"p":37,"q":916},{"start":33920,"end":33941,"p":31,"q":1094},{"start":33942,"end":33961,"p":47,"q":722},{"start":33962,"end":33986,"p":29,"q":1171},{"start":33987,"end":34008,"p":47,"q":723},{"start":34009,"end":34034,"p":31,"q":1097},{"start":34035,"end":34057,"p":41,"q":830},{"start":34058,"end":34083,"p":43,"q":792},{"start":34084,"end":34106,"p":53,"q":643},{"start":34107,"end":34131,"p":29,"q":1176},{"start":34132,"end":34158,"p":31,"q":1101},{"start":34159,"end":34180,"p":41,"q":833},{"start":34181,"end":34196,"p":47,"q":727},{"start":34197,"end":34221,"p":41,"q":834},{"start":34222,"end":34247,"p":29,"q":1180},{"start":34248,"end":34265,"p":53,"q":646},{"start":34266,"end":34290,"p":47,"q":729},{"start":34291,"end":34313,"p":31,"q":1106},{"start":34314,"end":34337,"p":47,"q":730},{"start":34338,"end":34363,"p":29,"q":1184},{"start":34364,"end":34385,"p":41,"q":838},{"start":34386,"end":34406,"p":31,"q":1109},{"start":34407,"end":34431,"p":47,"q":732},{"start":34432,"end":34450,"p":29,"q":1187},{"start":34451,"end":34477,"p":53,"q":650},{"start":34478,"end":34499,"p":31,"q":1112},{"start":34500,"end":34525,"p":47,"q":734},{"start":34526,"end":34549,"p":41,"q":842},{"start":34550,"end":34572,"p":47,"q":735},{"start":34573,"end":34599,"p":43,"q":804},{"start":34600,"end":34624,"p":29,"q":1193},{"start":34625,"end":34642,"p":43,"q":805},{"start":34643,"end":34666,"p":47,"q":737},{"start":34667,"end":34689,"p":53,"q":654},{"start":34690,"end":34716,"p":31,"q":1119},{"start":34717,"end":34742,"p":53,"q":655},{"start":34743,"end":34769,"p":29,"q":1198},{"start":34770,"end":34795,"p":41,"q":848},{"start":34796,"end":34814,"p":43,"q":809},{"start":34815,"end":34840,"p":31,"q":1123},{"start":34841,"end":34857,"p":43,"q":810},{"start":34858,"end":34881,"p":37,"q":942},{"start":34882,"end":34902,"p":31,"q":1125},{"start":34903,"end":34918,"p":37,"q":943},{"start":34919,"end":34943,"p":29,"q":1204},{"start":34944,"end":34964,"p":31,"q":1127},{"start":34965,"end":34986,"p":43,"q":813},{"start":34987,"end":35007,"p":53,"q":660},{"start":35008,"end":35030,"p":29,"q":1207},{"start":35031,"end":35057,"p":31,"q":1130},{"start":35058,"end":35082,"p":41,"q":855},{"start":35083,"end":35103,"p":37,"q":948},{"start":35104,"end":35123,"p":41,"q":856},{"start":35124,"end":35150,"p":31,"q":1133},{"start":35151,"end":35177,"p":37,"q":950},{"start":35178,"end":35204,"p":29,"q":1213},{"start":35205,"end":35230,"p":47,"q":749},{"start":35231,"end":35251,"p":37,"q":952},{"start":35252,"end":35277,"p":47,"q":750},{"start":35278,"end":35291,"p":29,"q":1216},{"start":35292,"end":35305,"p":31,"q":1138},{"start":35306,"end":35330,"p":43,"q":821},{"start":35331,"end":35349,"p":29,"q":1218},{"start":35350,"end":35373,"p":43,"q":822},{"start":35374,"end":35399,"p":37,"q":956},{"start":35400,"end":35418,"p":47,"q":753},{"start":35419,"end":35436,"p":29,"q":1221},{"start":35437,"end":35460,"p":31,"q":1143},{"start":35461,"end":35484,"p":53,"q":669},{"start":35485,"end":35510,"p":37,"q":959},{"start":35511,"end":35537,"p":53,"q":670},{"start":35538,"end":35559,"p":47,"q":756},{"start":35560,"end":35584,"p":31,"q":1147},{"start":35585,"end":35610,"p":29,"q":1227},{"start":35611,"end":35631,"p":43,"q":828},{"start":35632,"end":35658,"p":37,"q":963},{"start":35659,"end":35677,"p":31,"q":1150},{"start":35678,"end":35700,"p":47,"q":759},{"start":35701,"end":35726,"p":29,"q":1231},{"start":35727,"end":35749,"p":53,"q":674},{"start":35750,"end":35770,"p":31,"q":1153},{"start":35771,"end":35794,"p":47,"q":761},{"start":35795,"end":35820,"p":41,"q":873},{"start":35821,"end":35846,"p":43,"q":833},{"start":35847,"end":35871,"p":29,"q":1236},{"start":35872,"end":35894,"p":31,"q":1157},{"start":35895,"end":35917,"p":37,"q":970},{"start":35918,"end":35943,"p":41,"q":876},{"start":35944,"end":35961,"p":53,"q":678},{"start":35962,"end":35987,"p":29,"q":1240},{"start":35988,"end":36014,"p":53,"q":679},{"start":36015,"end":36029,"p":47,"q":766},{"start":36030,"end":36049,"p":31,"q":1162},{"start":36050,"end":36076,"p":47,"q":767},{"start":36077,"end":36103,"p":29,"q":1244},{"start":36104,"end":36123,"p":47,"q":768},{"start":36124,"end":36148,"p":41,"q":881},{"start":36149,"end":36173,"p":31,"q":1166},{"start":36174,"end":36190,"p":29,"q":1247},{"start":36191,"end":36217,"p":47,"q":770},{"start":36218,"end":36235,"p":31,"q":1168},{"start":36236,"end":36250,"p":37,"q":979},{"start":36251,"end":36277,"p":29,"q":1250},{"start":36278,"end":36297,"p":31,"q":1170},{"start":36298,"end":36324,"p":37,"q":981},{"start":36325,"end":36335,"p":29,"q":1252},{"start":36336,"end":36362,"p":43,"q":845},{"start":36363,"end":36385,"p":53,"q":686},{"start":36386,"end":36405,"p":43,"q":846},{"start":36406,"end":36422,"p":29,"q":1255},{"start":36423,"end":36448,"p":43,"q":847},{"start":36449,"end":36472,"p":37,"q":985},{"start":36473,"end":36499,"p":47,"q":776},{"start":36500,"end":36517,"p":41,"q":890},{"start":36518,"end":36544,"p":53,"q":689},{"start":36545,"end":36567,"p":29,"q":1260},{"start":36568,"end":36593,"p":47,"q":778},{"start":36594,"end":36620,"p":37,"q":989},{"start":36621,"end":36640,"p":41,"q":893},{"start":36641,"end":36663,"p":43,"q":852},{"start":36664,"end":36687,"p":47,"q":780},{"start":36688,"end":36712,"p":29,"q":1265},{"start":36713,"end":36734,"p":47,"q":781},{"start":36735,"end":36756,"p":53,"q":693},{"start":36757,"end":36781,"p":47,"q":782},{"start":36782,"end":36805,"p":37,"q":994},{"start":36806,"end":36828,"p":29,"q":1269},{"start":36829,"end":36855,"p":31,"q":1188},{"start":36856,"end":36879,"p":37,"q":996},{"start":36880,"end":36886,"p":29,"q":1271}]}
