{
  "classification_mode": "exhaustive",
  "classified_groups": 10000,
  "classified_weight": 111285,
  "classified_words": 10000,
  "elapsed_seconds": 1486.335896,
  "endpoint_groups": 20,
  "example_words": {},
  "first_classified_group_index": 260001,
  "first_classified_word_index": 260001,
  "last_classified_group_index": 270000,
  "last_classified_word_index": 270000,
  "max_total_mixed": 6,
  "min_total_mixed": 6,
  "mixed_example_words": [],
  "mixed_status_words": 0,
  "n": 99,
  "outside_cover_shells": 5867040,
  "profile_groups": null,
  "quotient": "word",
  "quotient_groups": 418260,
  "radicand": 1,
  "reps_per_group": 1,
  "reps_per_word": 1,
  "skip_classified_groups": 260000,
  "skip_classified_words": 260000,
  "status_group_counts": {
    "corner-label-violation": 5173,
    "pinch-sector-obstruction": 900,
    "split-corner-label-obstruction": 3927
  },
  "status_signatures": {
    "{\"corner-label-violation\": 10}": 225,
    "{\"corner-label-violation\": 11}": 45,
    "{\"corner-label-violation\": 12}": 280,
    "{\"corner-label-violation\": 13}": 45,
    "{\"corner-label-violation\": 14}": 180,
    "{\"corner-label-violation\": 15}": 65,
    "{\"corner-label-violation\": 16}": 270,
    "{\"corner-label-violation\": 17}": 45,
    "{\"corner-label-violation\": 18}": 260,
    "{\"corner-label-violation\": 19}": 45,
    "{\"corner-label-violation\": 20}": 180,
    "{\"corner-label-violation\": 21}": 20,
    "{\"corner-label-violation\": 24}": 170,
    "{\"corner-label-violation\": 27}": 20,
    "{\"corner-label-violation\": 30}": 80,
    "{\"corner-label-violation\": 32}": 90,
    "{\"corner-label-violation\": 33}": 20,
    "{\"corner-label-violation\": 36}": 60,
    "{\"corner-label-violation\": 3}": 120,
    "{\"corner-label-violation\": 40}": 90,
    "{\"corner-label-violation\": 48}": 90,
    "{\"corner-label-violation\": 4}": 90,
    "{\"corner-label-violation\": 6}": 1363,
    "{\"corner-label-violation\": 8}": 1320,
    "{\"pinch-sector-obstruction\": 8}": 900,
    "{\"split-corner-label-obstruction\": 12}": 200,
    "{\"split-corner-label-obstruction\": 15}": 40,
    "{\"split-corner-label-obstruction\": 18}": 160,
    "{\"split-corner-label-obstruction\": 21}": 40,
    "{\"split-corner-label-obstruction\": 24}": 160,
    "{\"split-corner-label-obstruction\": 27}": 40,
    "{\"split-corner-label-obstruction\": 30}": 160,
    "{\"split-corner-label-obstruction\": 33}": 40,
    "{\"split-corner-label-obstruction\": 36}": 120,
    "{\"split-corner-label-obstruction\": 3}": 240,
    "{\"split-corner-label-obstruction\": 6}": 2727
  },
  "status_weight_counts": {
    "corner-label-violation": 64923,
    "pinch-sector-obstruction": 7200,
    "split-corner-label-obstruction": 39162
  },
  "tile": [
    25,
    11,
    30
  ],
  "word_count_mismatches": [],
  "word_groups": 418260
}
